odoo/addons/delivery_schenker/README.rst
odoo/addons/delivery_schenker/__init__.py
odoo/addons/delivery_schenker/__manifest__.py
odoo/addons/delivery_schenker/api/fat_bookingWebServiceV1_1.wsdl
odoo/addons/delivery_schenker/api/fat_trackingWebServiceV2.wsdl
odoo/addons/delivery_schenker/api/prod_bookingWebServiceV1_1.wsdl
odoo/addons/delivery_schenker/api/prod_trackingWebServiceV2.wsdl
odoo/addons/delivery_schenker/data/delivery_schenker_data.xml
odoo/addons/delivery_schenker/i18n/delivery_schenker.pot
odoo/addons/delivery_schenker/i18n/es.po
odoo/addons/delivery_schenker/i18n/it.po
odoo/addons/delivery_schenker/models/__init__.py
odoo/addons/delivery_schenker/models/delivery_carrier.py
odoo/addons/delivery_schenker/models/schenker_request.py
odoo/addons/delivery_schenker/models/stock_package_type.py
odoo/addons/delivery_schenker/models/stock_picking.py
odoo/addons/delivery_schenker/readme/CONFIGURE.md
odoo/addons/delivery_schenker/readme/CONTRIBUTORS.md
odoo/addons/delivery_schenker/readme/DESCRIPTION.md
odoo/addons/delivery_schenker/readme/INSTALL.md
odoo/addons/delivery_schenker/readme/ROADMAP.md
odoo/addons/delivery_schenker/readme/USAGE.md
odoo/addons/delivery_schenker/static/description/icon.png
odoo/addons/delivery_schenker/static/description/icon.svg
odoo/addons/delivery_schenker/static/description/index.html
odoo/addons/delivery_schenker/tests/__init__.py
odoo/addons/delivery_schenker/views/delivery_schenker_view.xml
odoo/addons/delivery_schenker/views/stock_picking_views.xml
odoo_addon_delivery_schenker-18.0.1.0.0.4.dist-info/METADATA
odoo_addon_delivery_schenker-18.0.1.0.0.4.dist-info/WHEEL
odoo_addon_delivery_schenker-18.0.1.0.0.4.dist-info/top_level.txt
odoo_addon_delivery_schenker-18.0.1.0.0.4.dist-info/RECORD
